{"zingmp3.vn":{"/":{"zmp3_app_version.1":{"key":"zmp3_app_version.1","value":"1825","expires":"2024-01-20T09:21:07.000Z","maxAge":31536000,"domain":"zingmp3.vn","path":"/","hostOnly":false,"creation":"2023-01-20T09:21:07.627Z","lastAccessed":"2023-01-20T09:21:07.627Z"},"zmp3_rqid":{"key":"zmp3_rqid","value":"MHw3Ny4yMzQdUngMTkzLjg0fHYxLjgdUngMjV8MTY3NDIwNjQ2NzE3OQ","expires":"2023-03-26T09:21:07.000Z","maxAge":5616000,"domain":"zingmp3.vn","path":"/","secure":true,"httpOnly":true,"hostOnly":false,"creation":"2023-01-20T09:21:07.639Z","lastAccessed":"2023-01-20T09:21:07.639Z"}}}}